README.md
setup.py
automl/__init__.py
automl/combinators.py
automl/constants.py
automl/expression.py
automl/model.py
automl/pipeline.py
automl/data/__init__.py
automl/data/dataset.py
automl/data/loader.py
automl/feature/__init__.py
automl/feature/generators.py
automl/feature/selector.py
automl/hyperparam/__init__.py
automl/hyperparam/optimization.py
automl/hyperparam/templates.py
onepanel_automl.egg-info/PKG-INFO
onepanel_automl.egg-info/SOURCES.txt
onepanel_automl.egg-info/dependency_links.txt
onepanel_automl.egg-info/requires.txt
onepanel_automl.egg-info/top_level.txt