Metadata-Version: 1.1
Name: onepanel-automl
Version: 0.1.4
Summary: Automated Machine Learning Framework
Home-page: UNKNOWN
Author: Onepanel, Inc.
Author-email: info@onepanel.io
License: License :: Other/Proprietary License
Platform: UNKNOWN
Classifier: Topic :: Scientific/Engineering :: Artificial Intelligence
Classifier: Development Status :: 3 - Alpha
Classifier: Intended Audience :: Developers
Classifier: Operating System :: POSIX :: Linux
Classifier: Programming Language :: Python :: 3.6
